getKhoa/GanerateData.py
getKhoa/GenerateData.py
getKhoa/__inIt__.py
getKhoa-0.0.0.9.dist-info/METADATA
getKhoa-0.0.0.9.dist-info/WHEEL
getKhoa-0.0.0.9.dist-info/top_level.txt
getKhoa-0.0.0.9.dist-info/RECORD
